README.rst
pyproject.toml
setup.py
obr/__init__.py
obr/client.py
obr/event.py
obr/fleet.py
obr/handler.py
obr/thread.py
obr.egg-info/PKG-INFO
obr.egg-info/SOURCES.txt
obr.egg-info/dependency_links.txt
obr.egg-info/top_level.txt