Metadata-Version: 2.1
Name: obr
Version: 51
Summary: OBR
Author-email: Bart Thate <bthate@dds.nl>
License: Public Domain
Project-URL: home, https://pypi.org/project/obr
Project-URL: bugs, https://github.com/bthate/obr/issues
Project-URL: source, https://github.com/bthate/obr
Classifier: Development Status :: 1 - Planning
Classifier: License :: Public Domain
Classifier: Programming Language :: Python
Classifier: Intended Audience :: Developers
Classifier: Topic :: Software Development :: Libraries :: Python Modules
